sqlite_export_for_ynab/__init__.py
sqlite_export_for_ynab/__main__.py
sqlite_export_for_ynab/_main.py
sqlite_export_for_ynab/py.typed
sqlite_export_for_ynab/ddl/__init__.py
sqlite_export_for_ynab/ddl/create-relations.sql
sqlite_export_for_ynab/ddl/drop-relations.sql
sqlite_export_for_ynab-1.6.0.dist-info/licenses/LICENSE
testing/__init__.py
testing/fixtures.py
tests/__init__.py
tests/_main_test.py
sqlite_export_for_ynab-1.6.0.dist-info/METADATA
sqlite_export_for_ynab-1.6.0.dist-info/WHEEL
sqlite_export_for_ynab-1.6.0.dist-info/entry_points.txt
sqlite_export_for_ynab-1.6.0.dist-info/top_level.txt
sqlite_export_for_ynab-1.6.0.dist-info/RECORD
