Metadata-Version: 2.4
Name: sqlite_export_for_ynab
Version: 1.6.0
Summary: SQLite Export for YNAB - Export YNAB Budget Data to SQLite
Home-page: https://github.com/mxr/sqlite-export-for-ynab
Author: Max R
Author-email: maxr@outlook.com
License: MIT
Keywords: ynab,sqlite,sql,budget,cli
Classifier: Programming Language :: Python :: 3
Classifier: Programming Language :: Python :: 3 :: Only
Classifier: Programming Language :: Python :: Implementation :: CPython
Classifier: Programming Language :: Python :: Implementation :: PyPy
Requires-Python: >=3.12
License-File: LICENSE
Requires-Dist: aiohttp>=3
Requires-Dist: tldm
Dynamic: license-file
